Metadata-Version: 2.1
Name: irails
Version: 1.6.4
Summary: Simple and elegant use of FastApi in MVC mode
Home-page: https://github.com/smjkzsl/irails
Author: Bruce chou
Author-email: smjkzsl@gmail.com
License: Apache License 2.0
Keywords: web framework,mvc framework,fastapi framework
Classifier: License :: OSI Approved :: Apache Software License
Classifier: Operating System :: OS Independent
Classifier: Programming Language :: Python :: 3.6
Classifier: Programming Language :: Python :: 3.7
Classifier: Programming Language :: Python :: 3.8
Classifier: Programming Language :: Python :: 3.9
Classifier: Programming Language :: Python :: 3.10
Classifier: Programming Language :: Python :: 3.11
Requires-Python: >=3.6
